[{"rarity":4,"rarity_name":"SSレア","category":0,"category_name":"キャラ解放武器","item":[{"name":"ナーゲルリング","drop_rate":"12.500","attribute":"2","kind":"1","incidence":null,"reward_id":1040009300,"character_name":"イシュミール"},{"name":"プロエリウム","drop_rate":"12.500","attribute":"2","kind":"1","incidence":null,"reward_id":1040019800,"character_name":"スツルム"},{"name":"ブロッサムアクス","drop_rate":"12.500","attribute":"2","kind":"4","incidence":null,"reward_id":1040306900,"character_name":"ヴェイン"},{"name":"モンタギュオウス","drop_rate":"12.500","attribute":"2","kind":"5","incidence":null,"reward_id":1040408900,"character_name":"ロミオ"},{"name":"氷晶杖","drop_rate":"12.500","attribute":"2","kind":"5","incidence":null,"reward_id":1040400900,"character_name":"リリィ"},{"name":"コマンダーピストル","drop_rate":"12.500","attribute":"2","kind":"6","incidence":null,"reward_id":1040512200,"character_name":"リーシャ"},{"name":"オフィーリア","drop_rate":"12.500","attribute":"2","kind":"9","incidence":null,"reward_id":1040813000,"character_name":"ジュリエット"},{"name":"ベスちゃんにんぎょう","drop_rate":"12.500","attribute":"2","kind":"9","incidence":null,"reward_id":1040811700,"character_name":"飛竜と吸血姫 ヴァンピィ＆ベス"}]}]
