[{"rarity":4,"rarity_name":"SSレア","category":0,"category_name":"キャラ解放武器","item":[{"name":"ウルレ・ラム","drop_rate":"12.500","attribute":"6","kind":"2","incidence":null,"reward_id":1040116700,"character_name":"サンドリヨン","is_season":false,"season_message":""},{"name":"白芍巾着","drop_rate":"12.500","attribute":"6","kind":"4","incidence":null,"reward_id":1040316100,"character_name":"イルザ","is_season":false,"season_message":""},{"name":"プルメリアンセプター","drop_rate":"12.500","attribute":"6","kind":"5","incidence":null,"reward_id":1040420700,"character_name":"マギサ","is_season":false,"season_message":""},{"name":"紫梓想憧","drop_rate":"12.500","attribute":"6","kind":"6","incidence":null,"reward_id":1040515900,"character_name":"アズサ","is_season":false,"season_message":""},{"name":"イマジナリーナックル","drop_rate":"12.500","attribute":"6","kind":"7","incidence":null,"reward_id":1040616700,"character_name":"ボーマン","is_season":false,"season_message":""},{"name":"ガーリッシュドルチェ","drop_rate":"12.500","attribute":"6","kind":"7","incidence":null,"reward_id":1040616500,"character_name":"マナマル","is_season":false,"season_message":""},{"name":"緋翔蒼舞扇","drop_rate":"12.500","attribute":"6","kind":"7","incidence":null,"reward_id":1040616800,"character_name":"永遠の親愛 ユエル＆ソシエ","is_season":false,"season_message":""},{"name":"第十一戌行刃","drop_rate":"12.500","attribute":"6","kind":"10","incidence":null,"reward_id":1040913900,"character_name":"ヴァジラ","is_season":false,"season_message":""}]}]
